{"nodes": [{"id": "index_spa_application", "label": "Single Page Application Frontend", "file_type": "code", "source_file": "static/index.html", "source_location": null, "source_url": null, "captured_at": null, "author": null, "contributor": null}, {"id": "index_sidebar_nav", "label": "Sidebar Navigation with 10 Views", "file_type": "code", "source_file": "static/index.html", "source_location": null, "source_url": null, "captured_at": null, "author": null, "contributor": null}, {"id": "index_monitoring_chart_view", "label": "Monitoring / Chart View", "file_type": "code", "source_file": "static/index.html", "source_location": null, "source_url": null, "captured_at": null, "author": null, "contributor": null}, {"id": "index_portfolio_view", "label": "Portfolio Management View", "file_type": "code", "source_file": "static/index.html", "source_location": null, "source_url": null, "captured_at": null, "author": null, "contributor": null}, {"id": "index_screening_view", "label": "Screening View with Multiple Sheets", "file_type": "code", "source_file": "static/index.html", "source_location": null, "source_url": null, "captured_at": null, "author": null, "contributor": null}, {"id": "index_historical_data_view", "label": "Historical Data View", "file_type": "code", "source_file": "static/index.html", "source_location": null, "source_url": null, "captured_at": null, "author": null, "contributor": null}, {"id": "index_alarms_view", "label": "Alarms Management View", "file_type": "code", "source_file": "static/index.html", "source_location": null, "source_url": null, "captured_at": null, "author": null, "contributor": null}, {"id": "index_maintenance_view", "label": "Database Maintenance View", "file_type": "code", "source_file": "static/index.html", "source_location": null, "source_url": null, "captured_at": null, "author": null, "contributor": null}, {"id": "index_google_sheet_view", "label": "Google Sheets Integration View", "file_type": "code", "source_file": "static/index.html", "source_location": null, "source_url": null, "captured_at": null, "author": null, "contributor": null}, {"id": "index_investing_view", "label": "Investing.com Portfolio View", "file_type": "code", "source_file": "static/index.html", "source_location": null, "source_url": null, "captured_at": null, "author": null, "contributor": null}, {"id": "index_configuration_view", "label": "Configuration Settings View", "file_type": "code", "source_file": "static/index.html", "source_location": null, "source_url": null, "captured_at": null, "author": null, "contributor": null}, {"id": "index_drawing_toolbar", "label": "Drawing Annotation Toolbar", "file_type": "code", "source_file": "static/index.html", "source_location": null, "source_url": null, "captured_at": null, "author": null, "contributor": null}, {"id": "index_chart_slots_multi", "label": "Multi-Chart Slots (up to 4)", "file_type": "code", "source_file": "static/index.html", "source_location": null, "source_url": null, "captured_at": null, "author": null, "contributor": null}, {"id": "index_fundamentals_section", "label": "Ticker Fundamentals Section", "file_type": "code", "source_file": "static/index.html", "source_location": null, "source_url": null, "captured_at": null, "author": null, "contributor": null}, {"id": "index_portfolio_management", "label": "Portfolio Dashboard and Positions Table", "file_type": "code", "source_file": "static/index.html", "source_location": null, "source_url": null, "captured_at": null, "author": null, "contributor": null}, {"id": "index_transaction_modal", "label": "Transaction Modal (BUY/SELL/SHORT/COVER)", "file_type": "code", "source_file": "static/index.html", "source_location": null, "source_url": null, "captured_at": null, "author": null, "contributor": null}, {"id": "index_dividend_modal", "label": "Dividend Entry Modal", "file_type": "code", "source_file": "static/index.html", "source_location": null, "source_url": null, "captured_at": null, "author": null, "contributor": null}, {"id": "index_coupon_modal", "label": "Coupon Entry Modal", "file_type": "code", "source_file": "static/index.html", "source_location": null, "source_url": null, "captured_at": null, "author": null, "contributor": null}, {"id": "index_cash_modal", "label": "Cash Deposit/Withdrawal Modal", "file_type": "code", "source_file": "static/index.html", "source_location": null, "source_url": null, "captured_at": null, "author": null, "contributor": null}, {"id": "index_alarm_modal", "label": "Alarm Configuration Modal", "file_type": "code", "source_file": "static/index.html", "source_location": null, "source_url": null, "captured_at": null, "author": null, "contributor": null}, {"id": "index_indicator_modal", "label": "Indicator Configuration Modal", "file_type": "code", "source_file": "static/index.html", "source_location": null, "source_url": null, "captured_at": null, "author": null, "contributor": null}, {"id": "index_lightweight_charts", "label": "Lightweight Charts Library v4.2.3", "file_type": "code", "source_file": "static/index.html", "source_location": null, "source_url": null, "captured_at": null, "author": null, "contributor": null}, {"id": "index_flatpickr", "label": "Flatpickr Date Picker Library", "file_type": "code", "source_file": "static/index.html", "source_location": null, "source_url": null, "captured_at": null, "author": null, "contributor": null}, {"id": "index_screening_base_sheet", "label": "Screening Base Sheet (Price + ROC 1)", "file_type": "code", "source_file": "static/index.html", "source_location": null, "source_url": null, "captured_at": null, "author": null, "contributor": null}, {"id": "index_screening_roc_sheet", "label": "ROC Multi-Period Analysis Sheet", "file_type": "code", "source_file": "static/index.html", "source_location": null, "source_url": null, "captured_at": null, "author": null, "contributor": null}, {"id": "index_screening_fundamental_sheet", "label": "Fundamentals Screening Sheet", "file_type": "code", "source_file": "static/index.html", "source_location": null, "source_url": null, "captured_at": null, "author": null, "contributor": null}, {"id": "index_screening_column_mgmt", "label": "Screening Column Management", "file_type": "code", "source_file": "static/index.html", "source_location": null, "source_url": null, "captured_at": null, "author": null, "contributor": null}, {"id": "index_ticker_mappings", "label": "Ticker Mappings (Yahoo-Investing) Maintenance", "file_type": "code", "source_file": "static/index.html", "source_location": null, "source_url": null, "captured_at": null, "author": null, "contributor": null}, {"id": "index_orphan_indicators", "label": "Orphan Indicators Management", "file_type": "code", "source_file": "static/index.html", "source_location": null, "source_url": null, "captured_at": null, "author": null, "contributor": null}], "edges": [{"source": "index_spa_application", "target": "index_sidebar_nav", "relation": "references", "confidence": "EXTRACTED", "confidence_score": 1.0, "source_file": "static/index.html", "source_location": null, "weight": 1.0}, {"source": "index_spa_application", "target": "index_monitoring_chart_view", "relation": "references", "confidence": "EXTRACTED", "confidence_score": 1.0, "source_file": "static/index.html", "source_location": null, "weight": 1.0}, {"source": "index_spa_application", "target": "index_portfolio_view", "relation": "references", "confidence": "EXTRACTED", "confidence_score": 1.0, "source_file": "static/index.html", "source_location": null, "weight": 1.0}, {"source": "index_spa_application", "target": "index_screening_view", "relation": "references", "confidence": "EXTRACTED", "confidence_score": 1.0, "source_file": "static/index.html", "source_location": null, "weight": 1.0}, {"source": "index_spa_application", "target": "index_historical_data_view", "relation": "references", "confidence": "EXTRACTED", "confidence_score": 1.0, "source_file": "static/index.html", "source_location": null, "weight": 1.0}, {"source": "index_spa_application", "target": "index_alarms_view", "relation": "references", "confidence": "EXTRACTED", "confidence_score": 1.0, "source_file": "static/index.html", "source_location": null, "weight": 1.0}, {"source": "index_spa_application", "target": "index_maintenance_view", "relation": "references", "confidence": "EXTRACTED", "confidence_score": 1.0, "source_file": "static/index.html", "source_location": null, "weight": 1.0}, {"source": "index_spa_application", "target": "index_google_sheet_view", "relation": "references", "confidence": "EXTRACTED", "confidence_score": 1.0, "source_file": "static/index.html", "source_location": null, "weight": 1.0}, {"source": "index_spa_application", "target": "index_investing_view", "relation": "references", "confidence": "EXTRACTED", "confidence_score": 1.0, "source_file": "static/index.html", "source_location": null, "weight": 1.0}, {"source": "index_spa_application", "target": "index_configuration_view", "relation": "references", "confidence": "EXTRACTED", "confidence_score": 1.0, "source_file": "static/index.html", "source_location": null, "weight": 1.0}, {"source": "index_monitoring_chart_view", "target": "index_drawing_toolbar", "relation": "references", "confidence": "EXTRACTED", "confidence_score": 1.0, "source_file": "static/index.html", "source_location": null, "weight": 1.0}, {"source": "index_monitoring_chart_view", "target": "index_chart_slots_multi", "relation": "references", "confidence": "EXTRACTED", "confidence_score": 1.0, "source_file": "static/index.html", "source_location": null, "weight": 1.0}, {"source": "index_monitoring_chart_view", "target": "index_fundamentals_section", "relation": "references", "confidence": "EXTRACTED", "confidence_score": 1.0, "source_file": "static/index.html", "source_location": null, "weight": 1.0}, {"source": "index_monitoring_chart_view", "target": "index_lightweight_charts", "relation": "references", "confidence": "EXTRACTED", "confidence_score": 1.0, "source_file": "static/index.html", "source_location": null, "weight": 1.0}, {"source": "index_monitoring_chart_view", "target": "index_indicator_modal", "relation": "references", "confidence": "EXTRACTED", "confidence_score": 1.0, "source_file": "static/index.html", "source_location": null, "weight": 1.0}, {"source": "index_screening_view", "target": "index_screening_base_sheet", "relation": "references", "confidence": "EXTRACTED", "confidence_score": 1.0, "source_file": "static/index.html", "source_location": null, "weight": 1.0}, {"source": "index_screening_view", "target": "index_screening_roc_sheet", "relation": "references", "confidence": "EXTRACTED", "confidence_score": 1.0, "source_file": "static/index.html", "source_location": null, "weight": 1.0}, {"source": "index_screening_view", "target": "index_screening_fundamental_sheet", "relation": "references", "confidence": "EXTRACTED", "confidence_score": 1.0, "source_file": "static/index.html", "source_location": null, "weight": 1.0}, {"source": "index_screening_view", "target": "index_screening_column_mgmt", "relation": "references", "confidence": "EXTRACTED", "confidence_score": 1.0, "source_file": "static/index.html", "source_location": null, "weight": 1.0}, {"source": "index_portfolio_view", "target": "index_portfolio_management", "relation": "references", "confidence": "EXTRACTED", "confidence_score": 1.0, "source_file": "static/index.html", "source_location": null, "weight": 1.0}, {"source": "index_portfolio_view", "target": "index_transaction_modal", "relation": "references", "confidence": "EXTRACTED", "confidence_score": 1.0, "source_file": "static/index.html", "source_location": null, "weight": 1.0}, {"source": "index_portfolio_view", "target": "index_dividend_modal", "relation": "references", "confidence": "EXTRACTED", "confidence_score": 1.0, "source_file": "static/index.html", "source_location": null, "weight": 1.0}, {"source": "index_portfolio_view", "target": "index_coupon_modal", "relation": "references", "confidence": "EXTRACTED", "confidence_score": 1.0, "source_file": "static/index.html", "source_location": null, "weight": 1.0}, {"source": "index_portfolio_view", "target": "index_cash_modal", "relation": "references", "confidence": "EXTRACTED", "confidence_score": 1.0, "source_file": "static/index.html", "source_location": null, "weight": 1.0}, {"source": "index_alarms_view", "target": "index_alarm_modal", "relation": "references", "confidence": "EXTRACTED", "confidence_score": 1.0, "source_file": "static/index.html", "source_location": null, "weight": 1.0}, {"source": "index_maintenance_view", "target": "index_orphan_indicators", "relation": "references", "confidence": "EXTRACTED", "confidence_score": 1.0, "source_file": "static/index.html", "source_location": null, "weight": 1.0}, {"source": "index_maintenance_view", "target": "index_ticker_mappings", "relation": "references", "confidence": "EXTRACTED", "confidence_score": 1.0, "source_file": "static/index.html", "source_location": null, "weight": 1.0}, {"source": "errore_portfolio_collapsible_bug", "target": "index_portfolio_view", "relation": "references", "confidence": "EXTRACTED", "confidence_score": 1.0, "source_file": "static/index.html", "source_location": null, "weight": 1.0}, {"source": "index_spa_application", "target": "index_flatpickr", "relation": "references", "confidence": "EXTRACTED", "confidence_score": 1.0, "source_file": "static/index.html", "source_location": null, "weight": 1.0}, {"source": "index_screening_view", "target": "agantsmd_screeningsheet", "relation": "conceptually_related_to", "confidence": "INFERRED", "confidence_score": 0.85, "source_file": "static/index.html", "source_location": null, "weight": 0.85}, {"source": "index_screening_view", "target": "agantsmd_screeningvalue", "relation": "conceptually_related_to", "confidence": "INFERRED", "confidence_score": 0.85, "source_file": "static/index.html", "source_location": null, "weight": 0.85}, {"source": "index_portfolio_view", "target": "agantsmd_config_db", "relation": "conceptually_related_to", "confidence": "INFERRED", "confidence_score": 0.8, "source_file": "static/index.html", "source_location": null, "weight": 0.8}, {"source": "index_monitoring_chart_view", "target": "agantsmd_financelogic", "relation": "conceptually_related_to", "confidence": "INFERRED", "confidence_score": 0.8, "source_file": "static/index.html", "source_location": null, "weight": 0.8}, {"source": "index_investing_view", "target": "agantsmd_investingscraper", "relation": "conceptually_related_to", "confidence": "INFERRED", "confidence_score": 0.9, "source_file": "static/index.html", "source_location": null, "weight": 0.9}, {"source": "index_google_sheet_view", "target": "agantsmd_google_sheets", "relation": "conceptually_related_to", "confidence": "INFERRED", "confidence_score": 0.9, "source_file": "static/index.html", "source_location": null, "weight": 0.9}], "hyperedges": [{"id": "frontend_views_system", "label": "Frontend SPA Views System", "nodes": ["index_spa_application", "index_sidebar_nav", "index_monitoring_chart_view", "index_portfolio_view", "index_screening_view", "index_historical_data_view", "index_alarms_view", "index_maintenance_view", "index_google_sheet_view", "index_investing_view", "index_configuration_view"], "relation": "form", "confidence": "EXTRACTED", "confidence_score": 1.0, "source_file": "static/index.html"}, {"id": "portfolio_management_modals", "label": "Portfolio Management Modals", "nodes": ["index_portfolio_view", "index_portfolio_management", "index_transaction_modal", "index_dividend_modal", "index_coupon_modal", "index_cash_modal", "errore_portfolio_collapsible_bug"], "relation": "participate_in", "confidence": "EXTRACTED", "confidence_score": 1.0, "source_file": "static/index.html"}]}