{"nodes": [{"id": "verify_roc_caching_py", "label": "verify_roc_caching.py", "file_type": "code", "source_file": "verify_roc_caching.py", "source_location": "L1"}, {"id": "verify_roc_caching_verify_roc_caching", "label": "verify_roc_caching()", "file_type": "code", "source_file": "verify_roc_caching.py", "source_location": "L6"}], "edges": [{"source": "verify_roc_caching_py", "target": "finance_logic", "relation": "imports_from", "confidence": "EXTRACTED", "source_file": "verify_roc_caching.py", "source_location": "L1", "weight": 1.0}, {"source": "verify_roc_caching_py", "target": "database", "relation": "imports", "confidence": "EXTRACTED", "source_file": "verify_roc_caching.py", "source_location": "L2", "weight": 1.0}, {"source": "verify_roc_caching_py", "target": "json", "relation": "imports", "confidence": "EXTRACTED", "source_file": "verify_roc_caching.py", "source_location": "L3", "weight": 1.0}, {"source": "verify_roc_caching_py", "target": "datetime", "relation": "imports_from", "confidence": "EXTRACTED", "source_file": "verify_roc_caching.py", "source_location": "L4", "weight": 1.0}, {"source": "verify_roc_caching_py", "target": "verify_roc_caching_verify_roc_caching", "relation": "contains", "confidence": "EXTRACTED", "source_file": "verify_roc_caching.py", "source_location": "L6", "weight": 1.0}], "raw_calls": [{"caller_nid": "verify_roc_caching_verify_roc_caching", "callee": "FinanceLogic", "source_file": "verify_roc_caching.py", "source_location": "L7"}, {"caller_nid": "verify_roc_caching_verify_roc_caching", "callee": "init_db", "source_file": "verify_roc_caching.py", "source_location": "L8"}, {"caller_nid": "verify_roc_caching_verify_roc_caching", "callee": "SessionLocal", "source_file": "verify_roc_caching.py", "source_location": "L9"}, {"caller_nid": "verify_roc_caching_verify_roc_caching", "callee": "print", "source_file": "verify_roc_caching.py", "source_location": "L12"}, {"caller_nid": "verify_roc_caching_verify_roc_caching", "callee": "download_and_save_data", "source_file": "verify_roc_caching.py", "source_location": "L13"}, {"caller_nid": "verify_roc_caching_verify_roc_caching", "callee": "print", "source_file": "verify_roc_caching.py", "source_location": "L15"}, {"caller_nid": "verify_roc_caching_verify_roc_caching", "callee": "Ticker", "source_file": "verify_roc_caching.py", "source_location": "L19"}, {"caller_nid": "verify_roc_caching_verify_roc_caching", "callee": "print", "source_file": "verify_roc_caching.py", "source_location": "L22"}, {"caller_nid": "verify_roc_caching_verify_roc_caching", "callee": "now", "source_file": "verify_roc_caching.py", "source_location": "L23"}, {"caller_nid": "verify_roc_caching_verify_roc_caching", "callee": "run_modular_screening", "source_file": "verify_roc_caching.py", "source_location": "L24"}, {"caller_nid": "verify_roc_caching_verify_roc_caching", "callee": "now", "source_file": "verify_roc_caching.py", "source_location": "L25"}, {"caller_nid": "verify_roc_caching_verify_roc_caching", "callee": "print", "source_file": "verify_roc_caching.py", "source_location": "L26"}, {"caller_nid": "verify_roc_caching_verify_roc_caching", "callee": "print", "source_file": "verify_roc_caching.py", "source_location": "L27"}, {"caller_nid": "verify_roc_caching_verify_roc_caching", "callee": "count", "source_file": "verify_roc_caching.py", "source_location": "L32"}, {"caller_nid": "verify_roc_caching_verify_roc_caching", "callee": "filter", "source_file": "verify_roc_caching.py", "source_location": "L32"}, {"caller_nid": "verify_roc_caching_verify_roc_caching", "callee": "query", "source_file": "verify_roc_caching.py", "source_location": "L32"}, {"caller_nid": "verify_roc_caching_verify_roc_caching", "callee": "print", "source_file": "verify_roc_caching.py", "source_location": "L36"}, {"caller_nid": "verify_roc_caching_verify_roc_caching", "callee": "print", "source_file": "verify_roc_caching.py", "source_location": "L38"}, {"caller_nid": "verify_roc_caching_verify_roc_caching", "callee": "now", "source_file": "verify_roc_caching.py", "source_location": "L39"}, {"caller_nid": "verify_roc_caching_verify_roc_caching", "callee": "run_modular_screening", "source_file": "verify_roc_caching.py", "source_location": "L40"}, {"caller_nid": "verify_roc_caching_verify_roc_caching", "callee": "now", "source_file": "verify_roc_caching.py", "source_location": "L41"}, {"caller_nid": "verify_roc_caching_verify_roc_caching", "callee": "print", "source_file": "verify_roc_caching.py", "source_location": "L42"}, {"caller_nid": "verify_roc_caching_verify_roc_caching", "callee": "print", "source_file": "verify_roc_caching.py", "source_location": "L45"}, {"caller_nid": "verify_roc_caching_verify_roc_caching", "callee": "print", "source_file": "verify_roc_caching.py", "source_location": "L47"}, {"caller_nid": "verify_roc_caching_verify_roc_caching", "callee": "close", "source_file": "verify_roc_caching.py", "source_location": "L49"}]}